nvidia_tao_deploy/__init__.py
nvidia_tao_deploy/cv/__init__.py
nvidia_tao_deploy/cv/centerpose/__init__.py
nvidia_tao_deploy/cv/centerpose/centerpose_evaluator.py
nvidia_tao_deploy/cv/centerpose/dataloader.py
nvidia_tao_deploy/cv/centerpose/engine_builder.py
nvidia_tao_deploy/cv/centerpose/inferencer.py
nvidia_tao_deploy/cv/centerpose/iou3d.py
nvidia_tao_deploy/cv/centerpose/utils.py
nvidia_tao_deploy/cv/centerpose/entrypoint/__init__.py
nvidia_tao_deploy/cv/centerpose/entrypoint/centerpose.py
nvidia_tao_deploy/cv/centerpose/scripts/__init__.py
nvidia_tao_deploy/cv/centerpose/scripts/evaluate.py
nvidia_tao_deploy/cv/centerpose/scripts/gen_trt_engine.py
nvidia_tao_deploy/cv/centerpose/scripts/inference.py
nvidia_tao_deploy/cv/classification_pyt/__init__.py
nvidia_tao_deploy/cv/classification_pyt/entrypoint/__init__.py
nvidia_tao_deploy/cv/classification_pyt/entrypoint/classification_pyt.py
nvidia_tao_deploy/cv/classification_pyt/scripts/__init__.py
nvidia_tao_deploy/cv/classification_pyt/scripts/evaluate.py
nvidia_tao_deploy/cv/classification_pyt/scripts/gen_trt_engine.py
nvidia_tao_deploy/cv/classification_pyt/scripts/inference.py
nvidia_tao_deploy/cv/classification_tf1/__init__.py
nvidia_tao_deploy/cv/classification_tf1/dataloader.py
nvidia_tao_deploy/cv/classification_tf1/engine_builder.py
nvidia_tao_deploy/cv/classification_tf1/inferencer.py
nvidia_tao_deploy/cv/classification_tf1/entrypoint/__init__.py
nvidia_tao_deploy/cv/classification_tf1/entrypoint/classification_tf1.py
nvidia_tao_deploy/cv/classification_tf1/proto/__init__.py
nvidia_tao_deploy/cv/classification_tf1/proto/eval_config_pb2.py
nvidia_tao_deploy/cv/classification_tf1/proto/experiment_pb2.py
nvidia_tao_deploy/cv/classification_tf1/proto/lr_config_pb2.py
nvidia_tao_deploy/cv/classification_tf1/proto/model_config_pb2.py
nvidia_tao_deploy/cv/classification_tf1/proto/optimizer_config_pb2.py
nvidia_tao_deploy/cv/classification_tf1/proto/regularizer_config_pb2.py
nvidia_tao_deploy-6.25.11.dist-info/licenses/LICENSE
nvidia_tao_deploy-6.25.11.dist-info/METADATA
nvidia_tao_deploy-6.25.11.dist-info/WHEEL
nvidia_tao_deploy-6.25.11.dist-info/entry_points.txt
nvidia_tao_deploy-6.25.11.dist-info/top_level.txt
nvidia_tao_deploy-6.25.11.dist-info/RECORD
