Metadata-Version: 2.4
Name: nvidia-tao-deploy
Version: 6.25.11
Summary: NVIDIA's package for deploying models from TAO Toolkit.
Author: NVIDIA Corporation
License: NVIDIA Proprietary Software
Keywords: nvidia,tao,tensorrt
Classifier: Environment :: Console
Classifier: License :: Other/Proprietary License
Classifier: Natural Language :: English
Classifier: Operating System :: POSIX :: Linux
Classifier: Programming Language :: Python :: 3.6
Classifier: Programming Language :: Python :: 3.7
Classifier: Programming Language :: Python :: 3.8
Classifier: Topic :: Scientific/Engineering :: Artificial Intelligence
Requires-Python: ==3.12.*
License-File: LICENSE
Requires-Dist: absl-py==2.1.0
Requires-Dist: apispec==6.8.1
Requires-Dist: apispec-webframeworks==1.2.0
Requires-Dist: cuda-python==12.8.0
Requires-Dist: cupy-cuda12x==13.3.0
Requires-Dist: flake8==7.1.1
Requires-Dist: flask==3.1.0
Requires-Dist: flask_limiter==3.10.1
Requires-Dist: fontTools==4.55.8
Requires-Dist: h5py==3.12.1
Requires-Dist: hydra-core==1.3.2
Requires-Dist: marshmallow==3.26.1
Requires-Dist: marshmallow-enum==1.5.1
Requires-Dist: matplotlib==3.10.0
Requires-Dist: mpi4py==4.0.2
Requires-Dist: natsort==8.4.0
Requires-Dist: nvidia-eff==0.6.6
Requires-Dist: nvidia-eff-tao-encryption==0.1.9
Requires-Dist: nvidia-pyindex==1.0.9
Requires-Dist: onnx==1.17.0
Requires-Dist: onnxruntime==1.20.1
Requires-Dist: opencv-python==4.11.0.86
Requires-Dist: pipreqs==0.5.0
Requires-Dist: pyarmor==8.5.8
Requires-Dist: pyclipper==1.3.0.post6
Requires-Dist: pycocotools==2.0.8
Requires-Dist: pydocstyle==6.3.0
Requires-Dist: pyflakes==3.2.0
Requires-Dist: PyInstaller==6.11.1
Requires-Dist: pylint==3.3.4
Requires-Dist: pyrr==0.10.3
Requires-Dist: pytest==8.3.4
Requires-Dist: scipy==1.15.1
Requires-Dist: scikit-image==0.25.1
Requires-Dist: scikit-learn==1.6.1
Requires-Dist: seaborn==0.13.2
Requires-Dist: shapely==2.0.7
Dynamic: author
Dynamic: classifier
Dynamic: keywords
Dynamic: license
Dynamic: license-file
Dynamic: requires-dist
Dynamic: requires-python
Dynamic: summary
